{"updated":"2026-07-18T17:43:07.197Z","events":{"401857077":{"key":"New York Liberty|Indiana Fever","date":"2026-07-19T00:00Z","snaps":[{"mlA":"-142","mlH":"+120","spA":"-2.5","spAO":"-110","spH":"+2.5","spHO":"-110","tot":"180.5","oO":"-108","uO":"-112","t":1784385431997},{"mlA":"-130","mlH":"+110","spA":"-1.5","spAO":"-115","spH":"+1.5","spHO":"-105","tot":"181.5","oO":"-115","uO":"-105","t":1784396587197}]},"401857078":{"key":"Portland Fire|Minnesota Lynx","date":"2026-07-19T00:00Z","snaps":[{"mlA":"+550","mlH":"-800","spA":"+13.5","spAO":"-112","spH":"-13.5","spHO":"-108","tot":"175.5","oO":"-105","uO":"-115","t":1784385431997},{"mlA":"+525","mlH":"-750","spA":"+12.5","spAO":"-108","spH":"-12.5","spHO":"-112","tot":"173.5","oO":"-108","uO":"-112","t":1784396587197}]},"401857079":{"key":"Washington Mystics|Golden State Valkyries","date":"2026-07-19T00:30Z","snaps":[{"mlA":"+320","mlH":"-410","spA":"+9.5","spAO":"-118","spH":"-9.5","spHO":"-102","tot":"148.5","oO":"-105","uO":"-115","t":1784385431997},{"mlA":"+300","mlH":"-380","spA":"+8.5","spAO":"-110","spH":"-8.5","spHO":"-110","tot":"148.5","oO":"-108","uO":"-112","t":1784396587197}]},"401857080":{"key":"Los Angeles Sparks|Dallas Wings","date":"2026-07-19T17:00Z","snaps":[{"mlA":"+360","mlH":"-470","spA":"+9.5","spAO":"-110","spH":"-9.5","spHO":"-110","tot":"180.5","oO":"-110","uO":"-110","t":1784385431997}]},"401857081":{"key":"Chicago Sky|Atlanta Dream","date":"2026-07-19T20:00Z","snaps":[{"mlA":"+440","mlH":"-600","spA":"+10.5","spAO":"-110","spH":"-10.5","spHO":"-110","tot":"177.5","oO":"-110","uO":"-110","t":1784385431997}]}}}